pepeunit_client/__init__.py
pepeunit_client/abstract_clients.py
pepeunit_client/cipher.py
pepeunit_client/client.py
pepeunit_client/enums.py
pepeunit_client/file_manager.py
pepeunit_client/logger.py
pepeunit_client/pepeunit_mqtt_client.py
pepeunit_client/pepeunit_rest_client.py
pepeunit_client/schema_manager.py
pepeunit_client/settings.py
pepeunit_client-1.1.0.dist-info/METADATA
pepeunit_client-1.1.0.dist-info/WHEEL
pepeunit_client-1.1.0.dist-info/licenses/LICENSE
pepeunit_client-1.1.0.dist-info/RECORD
