Metadata-Version: 2.4
Name: pepeunit-client
Version: 1.1.0
Summary: Client Framework for Pepeunit
Project-URL: Homepage, https://pepeunit.com/
Project-URL: Issues, https://github.com/w7a8n1y4a/pepeunit_python_client/issues
Project-URL: Repository, https://github.com/w7a8n1y4a/pepeunit_python_client
Project-URL: Documentation, https://pepeunit.com/developer/libraries/python.html
Author-email: Ivan Serebrennikov <admin@silberworks.com>
License-Expression: AGPL-3.0-or-later
License-File: LICENSE
Classifier: Development Status :: 4 - Beta
Classifier: Intended Audience :: Developers
Classifier: License :: OSI Approved :: GNU Affero General Public License v3
Classifier: Operating System :: OS Independent
Classifier: Programming Language :: Python :: 3
Classifier: Programming Language :: Python :: 3.8
Classifier: Programming Language :: Python :: 3.9
Classifier: Programming Language :: Python :: 3.10
Classifier: Programming Language :: Python :: 3.11
Classifier: Programming Language :: Python :: 3.12
Classifier: Topic :: Internet :: WWW/HTTP
Classifier: Topic :: Software Development :: Libraries :: Python Modules
Classifier: Topic :: System :: Networking
Requires-Python: >=3.8
Requires-Dist: cryptography>=44.0.0
Requires-Dist: psutil>=5.8.0; platform_system != 'emscripten'
Provides-Extra: all
Requires-Dist: httpx>=0.24.0; extra == 'all'
Requires-Dist: paho-mqtt>=1.6.0; extra == 'all'
Provides-Extra: mqtt
Requires-Dist: paho-mqtt>=1.6.0; extra == 'mqtt'
Provides-Extra: rest
Requires-Dist: httpx>=0.24.0; extra == 'rest'
